rusz/main.py
rusz-22.4.18.post6.dist-info/entry_points.txt
rusz-22.4.18.post6.dist-info/WHEEL
rusz-22.4.18.post6.dist-info/METADATA
rusz-22.4.18.post6.dist-info/RECORD
